openpysql/__init__.py
openpysql/app.py
openpysql-1.5.0.dist-info/LICENSE
openpysql-1.5.0.dist-info/METADATA
openpysql-1.5.0.dist-info/WHEEL
openpysql-1.5.0.dist-info/top_level.txt
openpysql-1.5.0.dist-info/RECORD
