Metadata-Version: 2.1
Name: openpysql
Version: 1.5.0
Summary: A Python module for connecting to SQLite and MySQL databases and executing SQL queries.
Author-email: joumaico <joumaico@gmx.com>
License: MIT License
Project-URL: Homepage, https://github.com/joumaico/openpysql
Classifier: License :: OSI Approved :: MIT License
Classifier: Programming Language :: Python
Classifier: Programming Language :: Python :: 3
Requires-Python: >=3.10
License-File: LICENSE
Requires-Dist: bcrypt (>=4.0.1)
Requires-Dist: PyMySQL (>=1.0.2)
